<suite name="Suite">
    <test name = "Delivery Rate SetUp">
        <classes>
            <class name="CROWN.CICOD.LYTE.DeliveryRateCardSetUp.DELIVERY_RATE_CARD_SetUp"/>
        </classes>
    </test>

    <test name = "Order History">
        <classes>
            <class name="CROWN.CICOD.LYTE.OrderHistory.Downloadorderhistory"/>
            <class name="CROWN.CICOD.LYTE.OrderHistory.VIEW_ORDER_HISTORY"/>
        </classes>
    </test>

    <test name = "Create Order">
        <classes>
            <class name="CROWN.CICOD.LYTE.CreateOrder.CREATECUSTOMER"/>
            <class name="CROWN.CICOD.LYTE.CreateOrder.CREATE_ORDER_FROM_EXISTING_CUSTOMER"/>
            <class name="CROWN.CICOD.LYTE.CreateOrder.SEARCH_EXISTING_CUSTOMER"/>
            <class name="CROWN.CICOD.LYTE.CreateOrder.SELECT_DELIVERY_DETAILS"/>
            <class name="CROWN.CICOD.LYTE.CreateOrder.VIEW_CUSTOMER_DETAIL"/>
        </classes>
    </test>

    <test name = "DashBoard">
        <classes>
            <class name="CROWN.CICOD.LYTE.DashBoard.View_DashBoard_By_Date"/>
            <class name="CROWN.CICOD.LYTE.DashBoard.OrderFufilment"/>
            <class name="CROWN.CICOD.LYTE.DashBoard.Variance_Report_Dashboard"/>
        </classes>
    </test>
</suite>
